jacksonreport/__init__.py
jacksonreport/core/__init__.py
jacksonreport/core/dataDriver.py
jacksonreport/core/parameterized.py
jacksonreport/core/reRun.py
jacksonreport/core/resultPush.py
jacksonreport/core/sendEmail.py
jacksonreport/core/testResult.py
jacksonreport/core/testRunner.py
jacksonreport/templates/__init__.py
jacksonreport/templates/dingtalk.md
jacksonreport/templates/templates.html
jacksonreport/templates/templates03.html
jacksonreport/templates/templates2.html
jacksonreport/templates/templates3.html
jacksonreport-1.0.0.dist-info/LICENSE
jacksonreport-1.0.0.dist-info/METADATA
jacksonreport-1.0.0.dist-info/WHEEL
jacksonreport-1.0.0.dist-info/top_level.txt
jacksonreport-1.0.0.dist-info/RECORD
