Metadata-Version: 2.1
Name: jacksonreport
Version: 1.0.0
Summary: 封装好的接口自动化测试报告
Home-page: https://gitee.com/shanhaiqiu/jacksonreport.git
Author: jackson
Author-email: 1349983371@qq.com
License: UNKNOWN
Platform: UNKNOWN
Classifier: Programming Language :: Python :: 3
Classifier: License :: OSI Approved :: MIT License
Classifier: Operating System :: OS Independent
License-File: LICENSE
